{
  "type": "minecraft:crafting_shapeless",
  "category": "misc",
  "ingredients": [
    {
      "item": "minecraft:netherite_scrap"
    },
    {
      "item": "minecraft:netherite_scrap"
    },
    {
      "item": "minecraft:netherite_scrap"
    },
    {
      "item": "minecraft:netherite_scrap"
    },
    {
      "item": "minecraft:emerald"
    },
    {
      "item": "minecraft:emerald"
    },
    {
      "item": "minecraft:emerald"
    },
    {
      "item": "minecraft:emerald"
    },
    {
      "item": "minecraft:diamond_block"
    }
  ],
  "result": {
    "item": "emerald-is-useful:nemerite_ingot"
  },
  "show_notification": true
}